blot/__init__.py
blot/auth.py
blot/colors.py
blot/datagen.py
blot/date_tools.py
blot/exceptions.py
blot/extract.py
blot/helper.py
blot/offline.py
blot/pandastools.py
blot/plotlytools.py
blot/quant_figure.py
blot/ta.py
blot/themes.py
blot/tools.py
blot/utils.py
blot/version.py
blotly-1.0.8.data/data/README.md
helper/params.json
blotly-1.0.8.dist-info/METADATA
blotly-1.0.8.dist-info/WHEEL
blotly-1.0.8.dist-info/license.txt
blotly-1.0.8.dist-info/top_level.txt
blotly-1.0.8.dist-info/RECORD
