Metadata-Version: 2.1
Name: blotly
Version: 1.0.8
Summary: 基于cufflinks的绘图工具
Home-page: https://github.com/lotcher/blot
Author: bowaer
Author-email: cb229435444@outlook.com
License: MIT
Keywords: pandas,plotly,plotting
Platform: UNKNOWN
Classifier: Programming Language :: Python :: 3
Requires-Dist: numpy (>=1.9.2)
Requires-Dist: pandas (>=0.19.2)
Requires-Dist: plotly (>=4.9)
Requires-Dist: kaleido (>=0.2.1)
Requires-Dist: six (>=1.9.0)
Requires-Dist: colorlover (>=0.2.1)
Requires-Dist: setuptools (>=34.4.1)
Requires-Dist: ipython (>=5.3.0)
Requires-Dist: ipywidgets (>=7.0.0)
